{
	"configurations" : 
	[
		{
			"directories" : 
			[
				{
					"build" : ".",
					"minimumCMakeVersion" : 
					{
						"string" : "3.2"
					},
					"projectIndex" : 0,
					"source" : ".",
					"targetIndexes" : 
					[
						0,
						1,
						2,
						3,
						4,
						5
					]
				}
			],
			"name" : "",
			"projects" : 
			[
				{
					"directoryIndexes" : 
					[
						0
					],
					"name" : "MUTIL_MEDIA",
					"targetIndexes" : 
					[
						0,
						1,
						2,
						3,
						4,
						5
					]
				}
			],
			"targets" : 
			[
				{
					"directoryIndex" : 0,
					"id" : "amg8833::@6890427a1f51a3e7e1df",
					"jsonFile" : "target-amg8833-bb8c1b8ea0cc4b84cc2e.json",
					"name" : "amg8833",
					"projectIndex" : 0
				},
				{
					"directoryIndex" : 0,
					"id" : "audio_read_play::@6890427a1f51a3e7e1df",
					"jsonFile" : "target-audio_read_play-673ef3c0f98201d8590d.json",
					"name" : "audio_read_play",
					"projectIndex" : 0
				},
				{
					"directoryIndex" : 0,
					"id" : "audio_record_write::@6890427a1f51a3e7e1df",
					"jsonFile" : "target-audio_record_write-4e0fc09e4e83740c42cc.json",
					"name" : "audio_record_write",
					"projectIndex" : 0
				},
				{
					"directoryIndex" : 0,
					"id" : "vi_framebuffer::@6890427a1f51a3e7e1df",
					"jsonFile" : "target-vi_framebuffer-e4b129533d573285a3e6.json",
					"name" : "vi_framebuffer",
					"projectIndex" : 0
				},
				{
					"directoryIndex" : 0,
					"id" : "vi_multichannel::@6890427a1f51a3e7e1df",
					"jsonFile" : "target-vi_multichannel-88e8d7b4770e609cfe10.json",
					"name" : "vi_multichannel",
					"projectIndex" : 0
				},
				{
					"directoryIndex" : 0,
					"id" : "vi_signalchannel::@6890427a1f51a3e7e1df",
					"jsonFile" : "target-vi_signalchannel-9e06320c9da7d122c70c.json",
					"name" : "vi_signalchannel",
					"projectIndex" : 0
				}
			]
		}
	],
	"kind" : "codemodel",
	"paths" : 
	{
		"build" : "/home/swann/SDK/EXYNOS6818/Driver/MEDIA/build",
		"source" : "/home/swann/SDK/EXYNOS6818/Driver/MEDIA"
	},
	"version" : 
	{
		"major" : 2,
		"minor" : 0
	}
}
